Workbook

Sheet 재정규모
A1: 출처: 2024회계연도 결산개요 (통계편), 기획재정부
A2: 연차별 통합재정규모
A3: 구분 | B3: Classification | C3: 2013 | D3: 2014 | E3: 2015 | F3: 2016 | G3: 2017 | H3: 2018 | I3: 2019 | J3: 2020 | K3: 2021 | L3: 2022 | M3: 2023 | N3: 2024
A4: 공공부문(1+2) | B4: Public Sector | C4: 300237564 | D4: 312394133 | E4: 339351017 | F4: 354353560 | G4: 379809244 | H4: 407098761 | I4: 455849573 | J4: 517781119 | K4: 568112758 | L4: 652902345 | M4: 580354414 | N4: 603608529
A5: 1. 중앙정부 | B5: Central Gov't | C5: 296556584 | D5: 308980270 | E5: 336244037 | F5: 351546478 | G5: 376852563 | H5: 404491997 | I5: 452093975 | J5: 513462818 | K5: 565035470 | L5: 648857760 | M5: 575274127 | N5: 597525941
A6: 일반회계 | B6: General Account | C6: 191630847 | D6: 197379297 | E6: 205967651 | F6: 216929584 | G6: 225520099 | H6: 246425117 | I6: 277654704 | J6: 320760411 | K6: 339739951 | L6: 379872493 | M6: 343496722 | N6: 344518516
A7: 특별회계 | B7: Special Account | C7: 36652457 | D7: 36282746 | E7: 42043818 | F7: 39414738 | G7: 41542314 | H7: 39057169 | I7: 42324675 | J7: 44424545 | K7: 50221728 | L7: 50564453 | M7: 59552482 | N7: 67364188
A8: 기금 | B8: Gov't Fund | C8: 67938582 | D8: 75137509 | E8: 88042483 | F8: 94932880 | G8: 105753891 | H8: 112407351 | I8: 120955624 | J8: 147879359 | K8: 172510077 | L8: 206816084 | M8: 171197594 | N8: 185223570
A9: 세입세출외 | B9: Extra-Budget | C9: 334699 | D9: 180718 | E9: 190085 | F9: 269276 | G9: 4036259 | H9: 6602361 | I9: 11158971 | J9: 398504 | K9: 2563714 | L9: 11604731 | M9: 1027328 | N9: 419667
A10: 2. 비금융공기업 | B10: NFPEs | C10: 3680980 | D10: 3413863 | E10: 3106980 | F10: 2807082 | G10: 2956681 | H10: 2606764 | I10: 3755598 | J10: 4318300 | K10: 3077288 | L10: 4044584 | M10: 5080287 | N10: 6082588
A11: 기업회계 | B11: Gov't Enterprise | C11: 3680980 | D11: 3413863 | E11: 3106980 | F11: 2807082 | G11: 2956681 | H11: 2606764 | I11: 3755598 | J11: 4318300 | K11: 3077288 | L11: 4044584 | M11: 5080287 | N11: 6082588
A12: 기금 | B12: Gov't Fund
A13: 국내총생산(명목GDP, 억원) | B13: GDP | C13: 15008191 | D13: 15629289 | E13: 16580204 | F13: 17407796 | G13: 18356982 | H13: 18981926 | I13: 19244981 | J13: 19331524 | K13: 22219129 | L13: 23237815 | M13: 24011894 | N13: 25491207
A14: 국내총생산에 대한 비율 | B14: Ratio to GDP
A15: 공공부문 | B15: Public Sector | C15: 20 | D15: 20 | E15: 20.5 | F15: 20.4 | G15: 20.7 | H15: 21.4 | I15: 23.7 | J15: 26.8 | K15: 25.6 | L15: 28.1 | M15: 24.2 | N15: 23.7
A16: 중앙정부 | B16: Central Gov't | C16: 19.8 | D16: 19.8 | E16: 20.3 | F16: 20.2 | G16: 20.5 | H16: 21.3 | I16: 23.5 | J16: 26.6 | K16: 25.4 | L16: 27.9 | M16: 24 | N16: 23.4
B22: PPT
C23: 2015 | D23: 2016 | E23: 2017 | F23: 2018 | G23: 2019 | H23: 2020 | I23: 2021 | J23: 2022 | K23: 2023 | L23: 2024
A24: 예산 | B24: 일반회계 | C24: =E6/1000000 -> 205.96765 | D24: =F6/1000000 -> 216.92958 | E24: =G6/1000000 -> 225.5201 | F24: =H6/1000000 -> 246.42512 | G24: =I6/1000000 -> 277.6547 | H24: =J6/1000000 -> 320.76041 | I24: =K6/1000000 -> 339.73995 | J24: =L6/1000000 -> 379.87249 | ... L24: =N6/1000000 -> 344.51852
B25: 특별회계 | C25: =(E7+E10)/1000000 -> 45.150798 | D25: =(F7+F10)/1000000 -> 42.22182 | E25: =(G7+G10)/1000000 -> 44.498995 | F25: =(H7+H10)/1000000 -> 41.663933 | G25: =(I7+I10)/1000000 -> 46.080273 | H25: =(J7+J10)/1000000 -> 48.742845 | I25: =(K7+K10)/1000000 -> 53.299016 | J25: =(L7+L10)/1000000 -> 54.609037 | ... L25: =(N7+N10)/1000000 -> 73.446776
A26: 기금 | C26: =E8/1000000 -> 88.042483 | D26: =F8/1000000 -> 94.93288 | E26: =G8/1000000 -> 105.75389 | F26: =H8/1000000 -> 112.40735 | G26: =I8/1000000 -> 120.95562 | H26: =J8/1000000 -> 147.87936 | I26: =K8/1000000 -> 172.51008 | J26: =L8/1000000 -> 206.81608 | ... L26: =N8/1000000 -> 185.22357
A27: 세입세출 외 | C27: =E9/1000000 -> 0.190085 | D27: =F9/1000000 -> 0.269276 | E27: =G9/1000000 -> 4.036259 | F27: =H9/1000000 -> 6.602361 | G27: =I9/1000000 -> 11.158971 | H27: =J9/1000000 -> 0.398504 | I27: =K9/1000000 -> 2.563714 | J27: =L9/1000000 -> 11.604731 | ... L27: =N9/1000000 -> 0.419667
A28: 합계 | C28: =SUM(C24:C27) -> 339.35102 | D28: =SUM(D24:D27) -> 354.35356 | E28: =SUM(E24:E27) -> 379.80924 | F28: =SUM(F24:F27) -> 407.09876 | G28: =SUM(G24:G27) -> 455.84957 | H28: =SUM(H24:H27) -> 517.78112 | I28: =SUM(I24:I27) -> 568.11276 | J28: =SUM(J24:J27) -> 652.90235 | ... L28: =SUM(L24:L27) -> 603.60853
A29: GDP대비재정규모 | C29: =(E4*1000000)/(E13*100000000) -> 0.2046724 | D29: =(F4*1000000)/(F13*100000000) -> 0.20356027 | E29: =(G4*1000000)/(G13*100000000) -> 0.20690179 | F29: =(H4*1000000)/(H13*100000000) -> 0.21446652 | G29: =(I4*1000000)/(I13*100000000) -> 0.23686673 | H29: =(J4*1000000)/(J13*100000000) -> 0.26784289 | I29: =(K4*1000000)/(K13*100000000) -> 0.25568633 | J29: =(L4*1000000)/(L13*100000000) -> 0.28096546 | ... L29: =(N4*1000000)/(N13*100000000) -> 0.23679088

Sheet 국세수입
A1: 출처: 2024회계연도 결산개요 (통계편), 기획재정부
O2: PPT
A3: 구분 | B3: Classification | C3: 2015 | D3: 2016 | E3: 2017 | F3: 2018 | G3: 2019 | H3: 2020 | I3: 2021 | J3: 2022 | K3: 2023 | L3: 2024 | P3: 2015 | Q3: 2016 | R3: 2017 | S3: 2018 | T3: 2019 | U3: 2020 | V3: 2021 | W3: 2022 | X3: 2023 | Y3: 2024
A4: 합계 | B4: Tax Total | C4: 210832685 | D4: 235715955 | E4: 258511509 | F4: 285891986 | G4: 286031995 | H4: 276278187 | I4: 332504798 | J4: 385159576 | K4: 333939609 | L4: 326179304 | O4: 내국세 | P4: =SUM(C5,C24,C29,C33,C36)/1000000 -> 202.33726 | Q4: =SUM(D5,D24,D29,D33,D36)/1000000 -> 227.67056 | R4: =SUM(E5,E24,E29,E33,E36)/1000000 -> 249.98233 | S4: =SUM(F5,F24,F29,F33,F36)/1000000 -> 277.07678 | T4: =SUM(G5,G24,G29,G33,G36)/1000000 -> 278.14987 | U4: =SUM(H5,H24,H29,H33,H36)/1000000 -> 269.21965 | V4: =SUM(I5,I24,I29,I33,I36)/1000000 -> 324.2778 | W4: =SUM(J5,J24,J29,J33,J36)/1000000 -> 374.83546 | ... Y4: =SUM(L5,L24,L29,L33,L36)/1000000 -> 319.20704
A5: 가. 내국세 | B5: Internal Taxes | C5: 182012867 | D5: 206192573 | E5: 227768996 | F5: 254770201 | G5: 255804538 | H5: 246987193 | I5: 296445033 | J5: 352274995 | K5: 306059472 | L5: 298259369 | O5: 관세 | P5: =C21/1000000 -> 8.495424 | Q5: =D21/1000000 -> 8.045398 | R5: =E21/1000000 -> 8.529183 | S5: =F21/1000000 -> 8.815209 | T5: =G21/1000000 -> 7.882126 | U5: =H21/1000000 -> 7.05854 | V5: =I21/1000000 -> 8.227 | W5: =J21/1000000 -> 10.324118 | ... Y5: =L21/1000000 -> 6.972267
A6: (1) 직접세 | B6: Direct Taxes | C6: 110794855 | D6: 125962528 | E6: 141027508 | F6: 162757841 | G6: 164065433 | H6: 158997225 | I6: 199514775 | J6: 246912975 | K6: 210886593 | L6: 195227374 | O6: 총계 | P6: =SUM(P4:P5) -> 210.83269 | Q6: =SUM(Q4:Q5) -> 235.71596 | R6: =SUM(R4:R5) -> 258.51151 | S6: =SUM(S4:S5) -> 285.89199 | T6: =SUM(T4:T5) -> 286.032 | U6: =SUM(U4:U5) -> 276.27819 | V6: =SUM(V4:V5) -> 332.5048 | W6: =SUM(W4:W5) -> 385.15958 | ... Y6: =SUM(Y4:Y5) -> 326.1793
A7: ① 소득세 | B7: Income Taxes | C7: 60721761 | D7: 68497048 | E7: 75065760 | F7: 84461613 | G7: 83561997 | H7: 93108724 | I7: 114112339 | J7: 128748596 | K7: 115833024 | L7: 117417964 | O7: 세외수입 | P7: =세외수입!C4/1000000 -> 51.1056 | Q7: =세외수입!D4/1000000 -> 45.95862 | R7: =세외수입!E4/1000000 -> 34.389102 | S7: =세외수입!F4/1000000 -> 30.326496 | T7: =세외수입!G4/1000000 -> 46.207676 | U7: =세외수입!H4/1000000 -> 116.08885 | V7: =세외수입!I4/1000000 -> 105.85849 | W7: =세외수입!J4/1000000 -> 105.44584 | ... Y7: =세외수입!L4/1000000 -> 111.13852
A8: ② 법인세 | B8: Corporation Tax | C8: 45029483 | D8: 52115420 | E8: 59176596 | F8: 70937351 | G8: 72174278 | H8: 55513201 | I8: 70396282 | J8: 103570360 | K8: 80419515 | L8: 62511273 | O8: 총계 | P8: =SUM(P6:P7) -> 261.93829 | Q8: =SUM(Q6:Q7) -> 281.67458 | R8: =SUM(R6:R7) -> 292.90061 | S8: =SUM(S6:S7) -> 316.21848 | T8: =SUM(T6:T7) -> 332.23967 | U8: =SUM(U6:U7) -> 392.36704 | V8: =SUM(V6:V7) -> 438.36329 | W8: =SUM(W6:W7) -> 490.60542 | ... Y8: =SUM(Y6:Y7) -> 437.31782
A9: ③ 상속세 | B9: Inheritance Tax | C9: 5043611 | D9: 5350060 | E9: 6785152 | F9: 7358877 | G9: 8329158 | H9: 10375300 | I9: 15006154 | J9: 14594019 | K9: 14634054 | L9: 15298137
A10: ④ 자산재평가세 | B10: Asset Revaluation Tax | O10: 내국세 | P10: =P4/P$8 -> 0.77246158 | Q10: =Q4/Q$8 -> 0.80827514 | R10: =R4/R$8 -> 0.85347151 | S10: =S4/S$8 -> 0.87621943 | T10: =T4/T$8 -> 0.83719644 | U10: =U4/U$8 -> 0.68614236 | V10: =V4/V$8 -> 0.73974671 | W10: =W4/W$8 -> 0.76402633 | ... Y10: =Y4/Y$8 -> 0.72992003
A11: ⑤ 부당이득세 | B11: Excess Profit Tax | O11: 관세 | P11: =P5/P$8 -> 0.032432922 | Q11: =Q5/Q$8 -> 0.028562741 | R11: =R5/R$8 -> 0.029119717 | S11: =S5/S$8 -> 0.027876957 | T11: =T5/T$8 -> 0.023724217 | U11: =U5/U$8 -> 0.017989635 | V11: =V5/V$8 -> 0.018767539 | W11: =W5/W$8 -> 0.021043628 | ... Y11: =Y5/Y$8 -> 0.015943249
A12: ⑥ 토지초과이득세 | B12: Excess Increased Value of Land Tax | O12: 총계 | P12: =P6/P$8 -> 0.8048945 | Q12: =Q6/Q$8 -> 0.83683788 | R12: =R6/R$8 -> 0.88259122 | S12: =S6/S$8 -> 0.90409638 | T12: =T6/T$8 -> 0.86092065 | U12: =U6/U$8 -> 0.70413199 | V12: =V6/V$8 -> 0.75851424 | W12: =W6/W$8 -> 0.78506996 | ... Y12: =Y6/Y$8 -> 0.74586328
A13: (2) 간접세 | B13: Indirect Taxes | C13: 66829730 | D13: 75177561 | E13: 81456098 | F13: 86701333 | G13: 85020708 | H13: 82859679 | I13: 90824006 | J13: 97247719 | K13: 88676048 | L13: 95652532 | O13: 세외수입 | P13: =P7/P$8 -> 0.1951055 | Q13: =Q7/Q$8 -> 0.16316212 | R13: =R7/R$8 -> 0.11740878 | S13: =S7/S$8 -> 0.095903616 | T13: =T7/T$8 -> 0.13907935 | U13: =U7/U$8 -> 0.29586801 | V13: =V7/V$8 -> 0.24148576 | W13: =W7/W$8 -> 0.21493004 | ... Y13: =Y7/Y$8 -> 0.25413672
A14: ⑦ 부가가치세 | B14: Value Added Tax | C14: 54159098 | D14: 61828024 | E14: 67086975 | F14: 70009108 | G14: 70828268 | H14: 64882907 | I14: 71204565 | J14: 81626608 | K14: 73774862 | L14: 82235811 | O14: 총계 | P14: =P8/P$8 -> 1 | Q14: =Q8/Q$8 -> 1 | R14: =R8/R$8 -> 1 | S14: =S8/S$8 -> 1 | T14: =T8/T$8 -> 1 | U14: =U8/U$8 -> 1 | V14: =V8/V$8 -> 1 | W14: =W8/W$8 -> 1 | ... Y14: =Y8/Y$8 -> 1
A15: ⑧ 특별소비세 | B15: Special Consumption Tax | C15: 8000762 | D15: 8881274 | E15: 9860807 | F15: 10451027 | G15: 9719127 | H15: 9218116 | I15: 9363810 | J15: 9318244 | K15: 8820924 | L15: 8656553
A16: ⑨ 주세 | B16: Liquor Tax
A17: ⑩ 증권거래세 | B17: Security Transaction Tax | C17: 4669870 | D17: 4468083 | E17: 4508316 | F17: 6241198 | G17: 4473313 | H17: 8758656 | I17: 10255631 | J17: 6302867 | K17: 6080262 | L17: 4760168
A18: ⑪ 전화세 | B18: Telephone Tax
A19: (3) 과년도수입 | B19: Carry-Over from Previous Year | C19: 3434838 | D19: 4146690 | E19: 4389625 | F19: 4429774 | G19: 5872809 | H19: 4165083 | I19: 5146496 | J19: 7315527 | K19: 5699899 | L19: 6533443
A20: (4) 인지세 | B20: Stamp Tax | C20: 953446 | D20: 905795 | E20: 895764 | F20: 881253 | G20: 845588 | H20: 965206 | I20: 959756 | J20: 798775 | K20: 796932 | L20: 846020
A21: 나. 관세 | B21: Customs Duties | C21: 8495424 | D21: 8045398 | E21: 8529183 | F21: 8815209 | G21: 7882126 | H21: 7058540 | I21: 8227000 | J21: 10324118 | K21: 7288282 | L21: 6972267
A22: (1) 관세 | B22: Customs Duties | C22: 8199774 | D22: 7752896 | E22: 8142175 | F22: 8400631 | G22: 7403481 | H22: 6753183 | I22: 7865486 | J22: 9516553 | K22: 6997580 | L22: 6658516
A23: (2) 기타관세 | B23: Carry-Over from Previous Year | C23: 295650 | D23: 292502 | E23: 387009 | F23: 414578 | G23: 478646 | H23: 305357 | I23: 361514 | J23: 807565 | K23: 290703 | L23: 313751
A24: 다. 방위세 | B24: Defense Tax | C24: 183 | D24: 263 | E24: 331 | F24: 269 | G24: 271 | H24: 178 | I24: 287 | J24: 898 | K24: 137 | L24: 80
A25: (1) 방위세 | B25: Defense Tax | C25: -5
A26: (2) 관세분 | B26: On Customs Duties
A27: (3) 지방세분 | B27: On Local Taxes
A28: (4) 기타방위세 | B28: Other Defense Tax Previous Year | C28: 188 | D28: 263 | E28: 331 | F28: 269 | G28: 271 | H28: 178 | I28: 287 | J28: 898 | K28: 137 | L28: 80
A29: 라. 교통·에너지·환경세 | B29: Transportation-Energy-Environment Tax | C29: 14054594 | D29: 15303016 | E29: 15552612 | F29: 15334854 | G29: 14562707 | H29: 13937883 | I29: 16598390 | J29: 11116375 | K29: 10843590 | L29: 11389082
A30: (1) 교통·에너지·환경세 | B30: Transportation-Energy-Environment Tax | C30: 14049364 | D30: 15302418 | E30: 15524886 | F30: 15331969 | G30: 14559936 | H30: 13937462 | I30: 16598363 | J30: 11116082 | K30: 10842755 | L30: 11388682
A31: (2) 기타교통·에너지·환경세 | B31: Other Transportation-Energy-Environment Tax | C31: 5177 | D31: 554 | E31: 27715 | F31: 2873 | G31: 2760 | H31: 777 | I31: -36 | J31: 273 | K31: 811 | L31: 375
A32: (3) 기타교통세 | B32: Other Transport Tax | C32: 53 | D32: 44 | E32: 11 | F32: 12 | G32: 11 | H32: -356 | I32: 63 | J32: 20 | K32: 24 | L32: 24
A33: 마. 교육세 | B33: Educational Tax | C33: 4870582 | D33: 4880813 | E33: 5008413 | F33: 5098691 | G33: 5111088 | H33: 4693743 | I33: 5103866 | J33: 4644380 | K33: 5151619 | L33: 5373797
A34: (1) 교육세 | B34: Educational Tax | C34: 4837429 | D34: 4860087 | E34: 4987915 | F34: 5080573 | G34: 5095153 | H34: 4676131 | I34: 5086664 | J34: 4651560 | K34: 5131880 | L34: 5354230
A35: (2) 기타교육세 | B35: Other Educational Tax | C35: 33153 | D35: 20726 | E35: 20498 | F35: 18118 | G35: 15935 | H35: 17612 | I35: 17202 | J35: -7180 | K35: 19739 | L35: 19567
A36: 바. 종합부동산세 | B36: Comprehensive Real Estate Tax | C36: 1399035 | D36: 1293892 | E36: 1651974 | F36: 1872762 | G36: 2671265 | H36: 3600650 | I36: 6130222 | J36: 6798810 | K36: 4596509 | L36: 4184709
A37: (1) 종합부동산세 | B37: Comprehensive Real Estate Tax | C37: 1399035 | D37: 1293892 | E37: 1651974 | F37: 1872762 | G37: 2671265 | H37: 3600650 | I37: 6130222 | J37: 6798810 | K37: 4596509 | L37: 4184709

Sheet 세외수입
A1: 출처: 2024회계연도 결산개요 (통계편), 기획재정부
A3: 구분 | B3: Classification | C3: 2015 | D3: 2016 | E3: 2017 | F3: 2018 | G3: 2019 | H3: 2020 | I3: 2021 | J3: 2022 | K3: 2023 | L3: 2024
A4: 합계 | B4: Total | C4: 51105600 | D4: 45958620 | E4: 34389102 | F4: 30326496 | G4: 46207676 | H4: 116088854 | I4: 105858490 | J4: 105445844 | K4: 71237619 | L4: 111138516
A5: 가. 재산수입 | B5: Revenues from Gov't Owned Properties | C5: 1988760 | D5: 2734143 | E5: 3269601 | F5: 3770075 | G5: 3337187 | H5: 4486384 | I5: 6231211 | J5: 7445566 | K5: 3083060 | L5: 2994799
A6: (1) 토지및건물대여료 | B6: Rents from Land & Buildings | C6: 50947 | D6: 56139 | E6: 60005 | F6: 69561 | G6: 63295 | H6: 66753 | I6: 62813 | J6: 83620 | K6: 107391 | L6: 90229
A7: (2) 정부출자수입 | B7: Dividends & Profits | C7: 505268 | D7: 739455 | E7: 795030 | F7: 858792 | G7: 677992 | H7: 607104 | I7: 915711 | J7: 1682600 | K7: 941196 | L7: 1603347
A8: (3) 이자수입 | B8: Interest | C8: 526 | D8: 613 | E8: 254 | F8: 59 | G8: 3 | H8: 1618 | I8: 1
A9: (4) 기타재산수입 | B9: Others | C9: 1432019 | D9: 1937936 | E9: 2414312 | F9: 2841663 | G9: 2595897 | H9: 3810909 | I9: 5252686 | J9: 5679345 | K9: 2034472 | L9: 1301223
A10: 나. 경상이전수입 | B10: Current Transfer | C10: 5335529 | D10: 5445224 | E10: 6543041 | F10: 5720173 | G10: 4888638 | H10: 6298053 | I10: 6977520 | J10: 7787791 | K10: 8256978 | L10: 7755071
A11: (1) 연금수입 | B11: Contribution of Pension
A12: (2) 벌금및몰수금 | B12: Fine & Confiscation | C12: 2894941 | D12: 2945107 | E12: 3824330 | F12: 2727401 | G12: 2475519 | H12: 2739841 | I12: 3308956 | J12: 3473994 | K12: 3739144 | L12: 3415212
A13: (3) 변상금및위약금 | B13: Indemnities & Penalties | C13: 100184 | D13: 139345 | E13: 315857 | F13: 389209 | G13: 142079 | H13: 88439 | I13: 179640 | J13: 119501 | K13: 484 | L13: 26398
A14: (4) 가산금 | B14: Penalties to Delinquency | C14: 854131 | D14: 921135 | E14: 862992 | F14: 862617 | G14: 869685 | H14: 776517 | I14: 586565 | J14: 398645 | K14: 308711 | L14: 276241
A15: (5) 기타경상이전수입 | B15: Others | C15: 1486272 | D15: 1439637 | E15: 1539861 | F15: 1740946 | G15: 1401356 | H15: 2693256 | I15: 2902358 | J15: 3795652 | K15: 4208640 | L15: 4037221
A16: 다. 재화및용역판매수입 | B16: Sales of Goods & Services | C16: 631718 | D16: 624929 | E16: 645608 | F16: 716121 | G16: 756469 | H16: 728632 | I16: 711962 | J16: 793647 | K16: 977482 | L16: 1005628
A17: (1) 관유물대여료 | B17: Rents
A18: (2) 병원수입 | B18: Hospital Income | C18: 11229 | D18: 10942 | E18: 12611 | F18: 11077 | G18: 15452 | H18: 16233 | I18: 19932 | J18: 17119 | K18: 15442 | L18: 19010
A19: (3) 입장료수입 | B19: Admission Fee | C19: 3772 | D19: 3278 | E19: 4328 | F19: 4268 | G19: 4138 | H19: 1697 | I19: 1746 | J19: 5548 | K19: 6984 | L19: 4606
A20: (4) 면허료및수수료 | B20: License & Commission Fee | C20: 557661 | D20: 543232 | E20: 557210 | F20: 622414 | G20: 668597 | H20: 643671 | I20: 598485 | J20: 682080 | K20: 848042 | L20: 885998
A21: (5) 입학금및수업료 | B21: School Entrance & Tuition Fee | C21: 8406 | D21: 8583 | E21: 7962 | F21: 7287 | G21: 5339 | H21: 1992 | I21: 932 | J21: 1041 | K21: 1136 | L21: 1087
A22: (6) 공항항만및용수수입 | B22: Revenues from Airport Harbors & Water | C22: 2360 | D22: 3230 | E22: 4961 | F22: 8165 | G22: 7623 | H22: 7730 | I22: 5279 | J22: 7427 | K22: 7721 | L22: 5759
A23: (7) 실습수입 | B23: Revenues from School Experiment | C23: 4332 | D23: 3789 | E23: 3670 | F23: 3177 | G23: 3500 | H23: 3066 | I23: 2829 | J23: 3267 | K23: 2990 | L23: 3304
A24: (8) 기타잡수입 | B24: Others | C24: 43959 | D24: 51876 | E24: 54866 | F24: 59732 | G24: 51819 | H24: 54243 | I24: 82759 | J24: 77165 | K24: 95167 | L24: 85864
A25: (9) 벌금및몰수금 | B25: Fine & Confiscation
A26: 라. 수입대체경비 | B26: Receipts Tied to Expenses | C26: 350130 | D26: 353709 | E26: 343834 | F26: 372873 | G26: 379915 | H26: 127434 | I26: 130072 | J26: 168495 | K26: 258343 | L26: 253558
A27: 마. 관유물매각대 | B27: Sales Proceeds of Gov't Owned Properties | C27: 60415 | D27: 90372 | E27: 50140 | F27: 73411 | G27: 98622 | H27: 104098 | I27: 159921 | J27: 97908 | K27: 177600 | L27: 115609
A28: 바. 융자원금회수금 | B28: Collection of Loan Principal | C28: 2765 | D28: 4768 | E28: 2500 | F28: 2969 | G28: 2589 | H28: 2582 | I28: 498 | J28: 224 | K28: 90 | L28: 25
A29: 사. 국공채및차입금 | B29: National Bond & Borrowing | C29: 7335 | D29: 123942 | E29: 111702 | F29: 57565 | G29: 53995 | J29: 26322
A30: 아. 차관수입 | B30: Foreign Borrowing
A31: 자. 전년도이월금 | B31: Carry Over from Prev. Year | C31: 2815767 | D31: 2767578 | E31: 2703119 | F31: 3866808 | G31: 1677865 | H31: 1293644 | I31: 1424798 | J31: 2647663 | K31: 2793277 | L31: 2005589
A32: 차. 전입금및기타 | B32: Transfer Trust & Collection from Other A/C | C32: 39913181 | D32: 33813955 | E32: 20719557 | F32: 15746501 | G32: 35012396 | H32: 103048027 | I32: 90222508 | J32: 86478228 | K32: 55690789 | L32: 97008237

Sheet 기능별 세출실적
A1: 출처: 2024회계연도 결산개요 (통계편), 기획재정부,
A2: 4) 기능별 세출실적 (16쪽)
A5: 구분 | B5: 예산현액 | C5: 지출액 | D5: 구성비(%) | E5: 2023결산 | F5: 예산현액대비증감(A-B) | G5: D/A(%) | H5: 전년대비증감(B-C) | I5: E/C(%) | K5: 지출액 ranking
A6: 합계 | B6: 553997680 | C6: 529462952 | D6: 100 | E6: 490414468 | F6: 24534729 | G6: 4.4 | H6: 39048484 | I6: 8
A7: 일반·지방행정 | B7: 104266587 | C7: 101632562 | D7: 19.2 | E7: 88244442 | F7: 2634025 | G7: 2.5 | H7: 13388120 | I7: 15.2 | K7: =RANK(C7,$C$7:$C$22) -> 2
A8: 공공질서및안전 | B8: 24136885 | C8: 23762215 | D8: 4.5 | E8: 22170510 | F8: 374670 | G8: 1.6 | H8: 1591706 | I8: 7.2 | K8: =RANK(C8,$C$7:$C$22) -> 7
A9: 통일·외교 | B9: 4523968 | C9: 4344570 | D9: 0.8 | E9: 3494193 | F9: 179398 | G9: 4 | H9: 850377 | I9: 24.3 | K9: =RANK(C9,$C$7:$C$22) -> 15
A10: 국방 | B10: 62383283 | C10: 60035756 | D10: 11.3 | E10: 57637727 | F10: 2347527 | G10: 3.8 | H10: 2398029 | I10: 4.2 | K10: =RANK(C10,$C$7:$C$22) -> 4
A11: 교육 | B11: 109982241 | C11: 105275933 | D11: 19.9 | E11: 99436880 | F11: 4706308 | G11: 4.3 | H11: 5839053 | I11: 5.9 | K11: =RANK(C11,$C$7:$C$22) -> 1
A12: 문화및관광 | B12: 5234085 | C12: 4960532 | D12: 0.9 | E12: 4859367 | F12: 273552 | G12: 5.2 | H12: 101166 | I12: 2.1 | K12: =RANK(C12,$C$7:$C$22) -> 14
A13: 환경 | B13: 18138941 | C13: 16288580 | D13: 3.1 | E13: 15941175 | F13: 1850360 | G13: 10.2 | H13: 347405 | I13: 2.2 | K13: =RANK(C13,$C$7:$C$22) -> 9
A14: 사회복지 | B14: 85956604 | C14: 84533985 | D14: 16 | E14: 77853242 | F14: 1422619 | G14: 1.7 | H14: 6680743 | I14: 8.6 | K14: =RANK(C14,$C$7:$C$22) -> 3
A15: 보건 | B15: 16383421 | C15: 16266748 | D15: 3.1 | E15: 17228625 | F15: 116673 | G15: 0.7 | H15: -961877 | I15: -5.6 | K15: =RANK(C15,$C$7:$C$22) -> 10
A16: 농림수산 | B16: 30223068 | C16: 27612406 | D16: 5.2 | E16: 27916009 | F16: 2610662 | G16: 8.6 | H16: -303604 | I16: -1.1 | K16: =RANK(C16,$C$7:$C$22) -> 6
A17: 산업·중소기업및에너지 | B17: 18845738 | C17: 18397688 | D17: 3.5 | E17: 17601721 | F17: 448049 | G17: 2.4 | H17: 795968 | I17: 4.5 | K17: =RANK(C17,$C$7:$C$22) -> 8
A18: 교통및물류 | B18: 36440803 | C18: 33542973 | D18: 6.3 | E18: 27872563 | F18: 2897830 | G18: 8 | H18: 5670410 | I18: 20.3 | K18: =RANK(C18,$C$7:$C$22) -> 5
... A22: 예비비 | B22: 3183828 | C22: 638300 | D22: 0.1 | E22: 607200 | F22: 2545528 | G22: 80 | H22: 31100 | I22: 5.1 | K22: =RANK(C22,$C$7:$C$22) -> 16
A25: Top5 | B25: 구성비
A26: =A11 -> 교육 | B26: =D11 -> 19.9
A27: =A7 -> 일반·지방행정 | B27: =D7 -> 19.2
A28: =A14 -> 사회복지 | B28: =D14 -> 16
A29: =A10 -> 국방 | B29: =D10 -> 11.3
A30: =A18 -> 교통및물류 | B30: =D18 -> 6.3
A31: 기타 | B31: =100-SUM(B26:B30) -> 27.3

Sheet 성질별 분류
A1: 출처: 2024회계연도 결산개요 (통계편), 기획재정부,
A2: 4) 기능별 세출실적 (18쪽)
A5: 구분 | B5: 예산현액 | C5: 2024지출 | D5: 구성비(%) | E5: 2023결산 | F5: 예산현액대비증감 | G5: 증감률D/A(%) | H5: 전년대비증감 | I5: 전년대비증가율E/C(%) | K5: 지출액 ranking
A6: 합계 | B6: 553997680 | C6: 529462952 | D6: 100 | E6: 490414468 | F6: 24534729 | G6: 4.4 | H6: 39048484 | I6: 8
A7: 인건비 | B7: 47508735 | C7: 46867061 | D7: 8.9 | E7: 44810387 | F7: 641674 | G7: 1.4 | H7: 2056675 | I7: 4.6
A8: 물건비 | B8: 30571939 | C8: 29487082 | D8: 5.6 | E8: 29688699 | F8: 1084857 | G8: 3.5 | H8: -201617 | I8: -0.7
A9: 운영비 | B9: 24768329 | C9: 24067549 | D9: 4.5 | E9: 24143828 | F9: 700780 | G9: 2.8 | H9: -76279 | I9: -0.3
A10: 여비 | B10: 712495 | C10: 669753 | D10: 2.3 | E10: 656138 | F10: 42742 | G10: 6 | H10: 13615 | I10: 2.1
A11: 특수활동비 | B11: 123266 | C11: 119496 | D11: 0.4 | E11: 129558 | F11: 3771 | G11: 3.1 | H11: -10063 | I11: -7.8
A12: 업무추진비 | B12: 182195 | C12: 175306 | D12: 0.6 | E12: 172059 | F12: 6889 | G12: 3.8 | H12: 3247 | I12: 1.9
A13: 직무수행경비 | B13: 1064534 | C13: 1049580 | D13: 3.6 | E13: 1039090 | F13: 14954 | G13: 1.4 | H13: 10490 | I13: 1
A14: 연구용역비 | B14: 2677357 | C14: 2450432 | D14: 8.3 | E14: 2640074 | F14: 226925 | G14: 8.5 | H14: -189642 | I14: -7.2
A15: 안보비 | B15: 892100 | C15: 824491 | D15: 2.8 | E15: 804591 | F15: 67609 | G15: 7.6 | H15: 19900 | I15: 2.5
A16: 정보보안비 | B16: 151662 | C16: 130474 | D16: 0.4 | E16: 103360 | F16: 21188 | G16: 14 | H16: 27114 | I16: 26.2
A17: 이전지출 | B17: 318045703 | C17: 306528786 | D17: 57.9 | E17: 301866968 | F17: 11516917 | G17: 3.6 | H17: 4661818 | I17: 1.5
... A35: 예비비및기타 | B35: 3214230 | C35: 664671 | D35: 0.1 | E35: 633133 | F35: 2549559 | G35: 79.3 | H35: 31538 | I35: 5
A38: Top5 | B38: 구성비
A39: =A17 -> 이전지출 | B39: =D17 -> 57.9
A40: =A34 -> 전출금 | B40: =D34 -> 16
A41: =A7 -> 인건비 | B41: =D7 -> 8.9
A42: =A24 -> 자산취득 | B42: =D24 -> 7.5
A43: =A8 -> 물건비 | B43: =D8 -> 5.6
A44: 기타 | B44: =100-SUM(B39:B43) -> 4.1

Sheet 국가별 재정지출규모
A14: https://www.openfiscaldata.go.kr/op/ko/ug/UOPKOUGA03?ctzAcctStatsAmtDivCd=SNA02&statsYrFr=2023&statsYrTo=2023&langCd=ko
A16: 프랑스 | B16: 56.95 | D16: 한국 | E16: =B22 -> 35.16
A17: 이탈리아 | B17: 53.95 | D17: 미국 | E17: =B23 -> 39.13
A18: 포르투갈 | B18: 42.31 | D18: 일본 | E18: =B24 -> 40.6
A19: 영국 | B19: 47.13 | D19: 포르투갈 | E19: =B18 -> 42.31
A20: 스웨덴 | B20: 49.36 | D20: 영국 | E20: =B19 -> 47.13
A21: 독일 | B21: 48.38 | D21: 독일 | E21: =B21 -> 48.38
A22: 한국 | B22: 35.16 | D22: 스웨덴 | E22: =B20 -> 49.36
A23: 미국 | B23: 39.13 | D23: 이탈리아 | E23: =B17 -> 53.95
A24: 일본 | B24: 40.6 | D24: 프랑스 | E24: =B16 -> 56.95

Sheet 공공사회복지 지출 수준 비교
A5: 국회예산정책처, 나보포커스, 제 141호 (2026.03.1) 국제 비교로 본 한국 복지지출 수준과 신규 과제 (안태훈 분석관)
A6: https://www.nabo.go.kr/board/file/bulkDown.do?idx=9157&bid=68

Sheet 기능별 세출 (연도별)
A2: 구분 | B2: 2018 | C2: 2019 | D2: 2020 | E2: 2021 | F2: 2022 | G2: 2023 | H2: 2024
A3: 세입규모 | B3: 316218484 | C3: 332239672 | D3: 392367040 | E3: 438363287 | F3: 493867232 | G3: 407928318 | H3: 437317819
A4: 조세 | B4: 285891988 | C4: 286031996 | D4: 276278187 | E4: 332504797 | F4: 385159576 | G4: 333939610 | H4: 326179303
A5: 내국세 | B5: 254770202 | C5: 255804538 | D5: 246987193 | E5: 296445033 | F5: 352274995 | G5: 306059472 | H5: 298259369
A6: 관세 | B6: 8815210 | C6: 7882126 | D6: 7058540 | E6: 8227000 | F6: 10324118 | G6: 7288282 | H6: 6972267
A7: 방위세 | B7: 269 | C7: 271 | D7: 178 | E7: 287 | F7: 898 | G7: 137 | H7: 80
A8: 교통세 | B8: 15334854 | C8: 14562707 | D8: 13937883 | E8: 16598390 | F8: 11116375 | G8: 10843590 | H8: 11389082
A9: 교육세 | B9: 5098691 | C9: 5111088 | D9: 4693743 | E9: 5103866 | F9: 4644380 | G9: 5151619 | H9: 5373797
A10: 종합부동산세 | B10: 1872762 | C10: 2671265 | D10: 3600650 | E10: 6130222 | F10: 6798810 | G10: 4596509 | H10: 4184709
A11: 세외수입 | B11: 30268931 | C11: 46153681 | D11: 116088853 | E11: 105858490 | F11: 108681334 | G11: 73988708 | H11: 111138516
A12: 차관수입
A13: 국공채및차입금 | B13: 57565 | C13: 53995 | F13: 26322 | J13: 2018 | K13: 2019 | L13: 2020 | M13: 2021 | N13: 2022 | O13: 2023 | P13: 2024 | T13: 2018 | U13: 2019 | V13: 2020 | W13: 2021 | X13: 2022 | Y13: 2023 | Z13: 2024
A14: 세출규모 | B14: 299945984 | C14: 330884136 | D14: 385222988 | E14: 417720678 | F14: 485049157 | G14: 405886290 | H14: 435430470
A15: 일반지방행정 | B15: 64132405 | C15: 70882746 | D15: 86170021 | E15: 92407937 | F15: 103500736 | G15: 87029976 | H15: 99140080 | J15: =B15/B$14 -> 0.21381318 | K15: =C15/C$14 -> 0.21422226 | L15: =D15/D$14 -> 0.22368868 | M15: =E15/E$14 -> 0.22121945 | N15: =F15/F$14 -> 0.21338195 | O15: =G15/G$14 -> 0.2144196 | P15: =H15/H$14 -> 0.22768292 | S15: 사회복지 | T15: =SUM(J22) -> 0.16015034 | U15: =SUM(K22) -> 0.17125227 | V15: =SUM(L22) -> 0.18758528 | W15: =SUM(M22) -> 0.17074821 | X15: =SUM(N22) -> 0.15606602 | Y15: =SUM(O22) -> 0.18580314 | Z15: =SUM(P22) -> 0.18883548
A16: 공공질서및안전 | B16: 17685681 | C16: 18887154 | D16: 20081143 | E16: 20702631 | F16: 21476477 | G16: 20989733 | H16: 22355569 | J16: =B16/B$14 -> 0.058962886 | K16: =C16/C$14 -> 0.057080869 | L16: =D16/D$14 -> 0.052128621 | M16: =E16/E$14 -> 0.049560944 | N16: =F16/F$14 -> 0.044276908 | O16: =G16/G$14 -> 0.051713333 | P16: =H16/H$14 -> 0.051341306 | S16: 국방 | T16: =SUM(J18) -> 0.14314324 | U16: =SUM(K18) -> 0.14055392 | V16: =SUM(L18) -> 0.12488758 | W16: =SUM(M18) -> 0.12252813 | X16: =SUM(N18) -> 0.10816802 | Y16: =SUM(O18) -> 0.13833339 | Z16: =SUM(P18) -> 0.13547159
A17: 통일외교 | B17: 2487681 | C17: 2688181 | D17: 2711778 | E17: 2935460 | F17: 3140990 | G17: 3494193 | H17: 4344570 | J17: =B17/B$14 -> 0.0082937633 | K17: =C17/C$14 -> 0.0081242366 | L17: =D17/D$14 -> 0.007039502 | M17: =E17/E$14 -> 0.0070273275 | N17: =F17/F$14 -> 0.0064756117 | O17: =G17/G$14 -> 0.0086087978 | P17: =H17/H$14 -> 0.0099776435 | S17: 교육 | T17: =SUM(J19) -> 0.21385015 | U17: =SUM(K19) -> 0.21309843 | V17: =SUM(L19) -> 0.18317467 | W17: =SUM(M19) -> 0.18414318 | X17: =SUM(N19) -> 0.19419562 | Y17: =SUM(O19) -> 0.21259156 | Z17: =SUM(P19) -> 0.19889236
A18: 국방 | B18: 42935241 | C18: 46507063 | D18: 48109566 | E18: 51182533 | F18: 52466807 | G18: 56147628 | H18: 58988458 | J18: =B18/B$14 -> 0.14314324 | K18: =C18/C$14 -> 0.14055392 | L18: =D18/D$14 -> 0.12488758 | M18: =E18/E$14 -> 0.12252813 | N18: =F18/F$14 -> 0.10816802 | O18: =G18/G$14 -> 0.13833339 | P18: =H18/H$14 -> 0.13547159 | S18: 경제 | T18: =SUM(J24:J29) -> 0.15380336 | U18: =SUM(K24:K29) -> 0.14498986 | V18: =SUM(L24:L29) -> 0.1625809 | W18: =SUM(M24:M29) -> 0.16532132 | X18: =SUM(N24:N29) -> 0.19495 | Y18: =SUM(O24:O29) -> 0.12171921 | Z18: =SUM(P24:P29) -> 0.12722757
A19: 교육 | B19: 64143494 | C19: 70510890 | D19: 70563092 | E19: 76920412 | F19: 94194421 | G19: 86287999 | H19: 86603792 | J19: =B19/B$14 -> 0.21385015 | K19: =C19/C$14 -> 0.21309843 | L19: =D19/D$14 -> 0.18317467 | M19: =E19/E$14 -> 0.18414318 | N19: =F19/F$14 -> 0.19419562 | O19: =G19/G$14 -> 0.21259156 | P19: =H19/H$14 -> 0.19889236 | S19: 기타 | T19: =SUM(J15:J17,J20:J21,J23,J30) -> 0.3290529 | U19: =SUM(K15:K17,K20:K21,K23,K30) -> 0.33010552 | V19: =SUM(L15:L17,L20:L21,L23,L30) -> 0.34177157 | W19: =SUM(M15:M17,M20:M21,M23,M30) -> 0.35725916 | X19: =SUM(N15:N17,N20:N21,N23,N30) -> 0.34662035 | Y19: =SUM(O15:O17,O20:O21,O23,O30) -> 0.3415527 | Z19: =SUM(P15:P17,P20:P21,P23,P30) -> 0.349573
A20: 문화및관광 | B20: 2819017 | C20: 3237099 | D20: 3682217 | E20: 3967285 | F20: 4278457 | G20: 4448238 | H20: 4498254 | J20: =B20/B$14 -> 0.0093984155 | K20: =C20/C$14 -> 0.0097831798 | L20: =D20/D$14 -> 0.0095586637 | M20: =E20/E$14 -> 0.009497459 | N20: =F20/F$14 -> 0.0088206668 | O20: =G20/G$14 -> 0.010959321 | P20: =H20/H$14 -> 0.010330591
A21: 환경 | B21: 3588604 | C21: 4186156 | D21: 5279449 | E21: 5517787 | F21: 5784851 | G21: 5260757 | H21: 5475595 | J21: =B21/B$14 -> 0.011964168 | K21: =C21/C$14 -> 0.012651426 | L21: =D21/D$14 -> 0.013704917 | M21: =E21/E$14 -> 0.013209274 | N21: =F21/F$14 -> 0.011926319 | O21: =G21/G$14 -> 0.01296116 | P21: =H21/H$14 -> 0.012575131
A22: 사회복지 | B22: 48036452 | C22: 56664661 | D22: 72262163 | E22: 71325060 | F22: 75699690 | G22: 75414946 | H22: 82224721 | J22: =B22/B$14 -> 0.16015034 | K22: =C22/C$14 -> 0.17125227 | L22: =D22/D$14 -> 0.18758528 | M22: =E22/E$14 -> 0.17074821 | N22: =F22/F$14 -> 0.15606602 | O22: =G22/G$14 -> 0.18580314 | P22: =H22/H$14 -> 0.18883548
A23: 보건 | B23: 7417707 | C23: 8765343 | D23: 13183659 | E23: 23153440 | F23: 29370396 | G23: 16801462 | H23: 15762368 | J23: =B23/B$14 -> 0.024730143 | K23: =C23/C$14 -> 0.026490672 | L23: =D23/D$14 -> 0.034223448 | M23: =E23/E$14 -> 0.055428044 | N23: =F23/F$14 -> 0.06055138 | O23: =G23/G$14 -> 0.041394505 | P23: =H23/H$14 -> 0.036199506
A24: 농림수산 | B24: 9102720 | C24: 9421392 | D24: 10278984 | E24: 7206629 | F24: 6839900 | G24: 9194983 | H24: 9251480 | J24: =B24/B$14 -> 0.030347864 | K24: =C24/C$14 -> 0.028473387 | L24: =D24/D$14 -> 0.026683205 | M24: =E24/E$14 -> 0.017252268 | N24: =F24/F$14 -> 0.014101457 | O24: =G24/G$14 -> 0.022654086 | P24: =H24/H$14 -> 0.021246745
A25: 산업중소기업및에너지 | B25: 7212104 | C25: 8707407 | D25: 20342104 | E25: 28300984 | F25: 54720624 | G25: 11439996 | H25: 11666777 | J25: =B25/B$14 -> 0.024044676 | K25: =C25/C$14 -> 0.026315577 | L25: =D25/D$14 -> 0.052806049 | M25: =E25/E$14 -> 0.067750977 | N25: =F25/F$14 -> 0.11281459 | O25: =G25/G$14 -> 0.028185224 | P25: =H25/H$14 -> 0.026793662
A26: 교통및물류 | B26: 18802026 | C26: 17501589 | D26: 18321882 | E26: 18172496 | F26: 16663254 | G26: 12691950 | H26: 17055764 | J26: =B26/B$14 -> 0.062684707 | K26: =C26/C$14 -> 0.052893406 | L26: =D26/D$14 -> 0.047561757 | M26: =E26/E$14 -> 0.043503942 | N26: =F26/F$14 -> 0.034353743 | O26: =G26/G$14 -> 0.031269718 | P26: =H26/H$14 -> 0.039169891
A27: 통신 | B27: 348072 | C27: 354568 | D27: 434555 | E27: 583767 | F27: 1025036 | G27: 963709 | H27: 899859 | J27: =B27/B$14 -> 0.0011604489 | K27: =C27/C$14 -> 0.0010715775 | L27: =D27/D$14 -> 0.0011280609 | M27: =E27/E$14 -> 0.0013975056 | N27: =F27/F$14 -> 0.0021132621 | O27: =G27/G$14 -> 0.0023743325 | P27: =H27/H$14 -> 0.0020665963
A28: 국토및지역개발 | B28: 4510928 | C28: 5549322 | D28: 6449132 | E28: 7392871 | F28: 7534780 | G28: 7088677 | H28: 8756881 | J28: =B28/B$14 -> 0.015039135 | K28: =C28/C$14 -> 0.016771194 | L28: =D28/D$14 -> 0.016741296 | M28: =E28/E$14 -> 0.017698121 | N28: =F28/F$14 -> 0.015534054 | O28: =G28/G$14 -> 0.017464687 | P28: =H28/H$14 -> 0.020110859
A29: 과학기술 | B29: 6156850 | C29: 6440566 | D29: 6803243 | E29: 7401386 | F29: 7776737 | G29: 8024843 | H29: 7768001 | J29: =B29/B$14 -> 0.020526529 | K29: =C29/C$14 -> 0.019464717 | L29: =D29/D$14 -> 0.017660532 | M29: =E29/E$14 -> 0.017718505 | N29: =F29/F$14 -> 0.016032884 | O29: =G29/G$14 -> 0.019771161 | P29: =H29/H$14 -> 0.01783982
A30: 예비비 | B30: 567000 | C30: 580000 | D30: 550000 | E30: 550000 | F30: 576000 | G30: 607200 | H30: 638300 | J30: =B30/B$14 -> 0.0018903404 | K30: =C30/C$14 -> 0.0017528794 | L30: =D30/D$14 -> 0.0014277445 | M30: =E30/E$14 -> 0.0013166693 | N30: =F30/F$14 -> 0.0011875085 | O30: =G30/G$14 -> 0.0014959855 | P30: =H30/H$14 -> 0.0014659057

Sheet 조세부담률 변화 추이
A1: https://www.index.go.kr/unity/potal/main/EachDtlPageDetail.do?idx_cd=1122
A2: 통계표명: | B2: 조세부담률
A3: 단위: | B3: 조원
C4: 1990 | D4: 1991 | E4: 1992 | F4: 1993 | G4: 1994 | H4: 1995 | I4: 1996 | J4: 1997 | K4: 1998 | L4: 1999 | M4: 2000 | N4: 2001 | O4: 2002 | P4: 2003 | Q4: 2004 | R4: 2005 | S4: 2006 | T4: 2007 | U4: 2008 | V4: 2009 | W4: 2010 | X4: 2011 | Y4: 2012 | Z4: 2013 | AA4: 2014 | AB4: 2015 | AC4: 2016 | AD4: 2017 | AE4: 2018 | AF4: 2019 | AG4: 2020 | AH4: 2021 | AI4: 2022 | AJ4: 2023 | AK4: 2024 p)
A5: 경상GDP | C5: 206.7 | D5: 250.0 | E5: 286.4 | F5: 325.6 | G5: 385.0 | H5: 452.2 | I5: 507.8 | J5: 560.5 | K5: 556.8 | L5: 613.1 | M5: 675.7 | N5: 732.7 | O5: 813.2 | P5: 868.1 | Q5: 942.9 | R5: 995.2 | S5: 1,045.7 | T5: 1,134.5 | U5: 1,203.0 | V5: 1,255.3 | W5: 1,379.5 | X5: 1,448.6 | Y5: 1,504.7 | Z5: 1,570.9 | AA5: 1,638.5 | AB5: 1,740.8 | AC5: 1,833.0 | AD5: 1,934.2 | AE5: 2,007.0 | AF5: 2,040.6 | AG5: 2,058.5 | AH5: 2,221.9 | AI5: 2,323.8 | AJ5: 2,408.7 | AK5: 2,556.9
A6: 조세 | B6: 계 | C6: 33.2 | D6: 38.4 | E6: 44.7 | F6: 50.3 | G6: 60.5 | H6: 72.1 | I6: 82.4 | J6: 88.3 | K6: 84.9 | L6: 94.2 | M6: 113.5 | N6: 122.5 | O6: 135.5 | P6: 147.8 | Q6: 152.0 | R6: 163.4 | S6: 179.3 | T6: 205.0 | U6: 212.8 | V6: 209.7 | W6: 226.9 | X6: 244.7 | Y6: 257.0 | Z6: 255.7 | AA6: 267.2 | AB6: 288.9 | AC6: 318.1 | AD6: 345.8 | AE6: 377.9 | AF6: 383.9 | AG6: 387.6 | AH6: 456.9 | AI6: 514.5 | AJ6: 456.5 | AK6: 450.6
B7: (조세부담률,%) | C7: 16.1 | D7: 15.3 | E7: 15.6 | F7: 15.4 | G7: 15.7 | H7: 15.9 | I7: 16.2 | J7: 15.8 | K7: 15.3 | L7: 15.4 | M7: 16.8 | N7: 16.7 | O7: 16.7 | P7: 17.0 | Q7: 16.1 | R7: 16.4 | S7: 17.2 | T7: 18.1 | U7: 17.7 | V7: 16.7 | W7: 16.4 | X7: 16.9 | Y7: 17.1 | Z7: 16.3 | AA7: 16.3 | AB7: 16.6 | AC7: 17.4 | AD7: 17.9 | AE7: 18.8 | AF7: 18.8 | AG7: 18.8 | AH7: 20.6 | AI7: 22.1 | AJ7: 19.0 | AK7: 17.6
B8: 국세 | C8: 26.8 | D8: 30.3 | E8: 35.2 | F8: 39.3 | G8: 47.3 | H8: 56.8 | I8: 65.0 | J8: 69.9 | K8: 67.8 | L8: 75.7 | M8: 92.9 | N8: 95.8 | O8: 104.0 | P8: 114.7 | Q8: 117.8 | R8: 127.5 | S8: 138.0 | T8: 161.4 | U8: 167.3 | V8: 164.5 | W8: 177.7 | X8: 192.4 | Y8: 203.0 | Z8: 201.9 | AA8: 205.5 | AB8: 217.9 | AC8: 242.6 | AD8: 265.4 | AE8: 293.6 | AF8: 293.5 | AG8: 285.5 | AH8: 344.1 | AI8: 395.9 | AJ8: 344.1 | AK8: 336.5
B9: 지방세 | C9: 6.4 | D9: 8.0 | E9: 9.5 | F9: 11.0 | G9: 13.2 | H9: 15.3 | I9: 17.4 | J9: 18.4 | K9: 17.1 | L9: 18.6 | M9: 20.6 | N9: 26.7 | O9: 31.5 | P9: 33.1 | Q9: 34.2 | R9: 36.0 | S9: 41.3 | T9: 43.4 | U9: 45.5 | V9: 45.2 | W9: 49.2 | X9: 52.3 | Y9: 53.9 | Z9: 53.8 | AA9: 61.7 | AB9: 71.0 | AC9: 75.5 | AD9: 80.4 | AE9: 84.3 | AF9: 90.5 | AG9: 102.0 | AH9: 112.8 | AI9: 118.6 | AJ9: 112.5 | AK9: 114.1
A10: 출처: | B10: * 국세, 지방세 실적 : 국세청.관세청「징수보고서」, 행정안전부「지방세 통계연감」
B11: * GDP : 한국은행, 25.6월 발표 국민계정 자료(신계열 기준, 2020년)
A12: 주석: | B12: * 한국은행 신계열 GDP 기준(2015년에서 2020년으로 기준년 개편)
C14: =C4 -> 1990 | D14: =H4 -> 1995 | E14: =M4 -> 2000 | F14: =R4 -> 2005 | G14: =W4 -> 2010 | H14: =AB4 -> 2015 | I14: =AG4 -> 2020 | J14: =AH4 -> 2021 | K14: =AI4 -> 2022 | L14: =AJ4 -> 2023 | M14: =AK4 -> 2024 p)
A15: 경상GDP | C15: =C5 -> 206.7 | D15: =H5 -> 452.2 | E15: =M5 -> 675.7 | F15: =R5 -> 995.2 | G15: =W5 -> 1,379.5 | H15: =AB5 -> 1,740.8 | I15: =AG5 -> 2,058.5 | J15: =AH5 -> 2,221.9 | K15: =AI5 -> 2,323.8 | L15: =AJ5 -> 2,408.7 | M15: =AK5 -> 2,556.9
A16: 조세 | B16: 계 | C16: =C6 -> 33.2 | D16: =H6 -> 72.1 | E16: =M6 -> 113.5 | F16: =R6 -> 163.4 | G16: =W6 -> 226.9 | H16: =AB6 -> 288.9 | I16: =AG6 -> 387.6 | J16: =AH6 -> 456.9 | K16: =AI6 -> 514.5 | L16: =AJ6 -> 456.5 | M16: =AK6 -> 450.6
B17: (조세부담률,%) | C17: =C7 -> 16.1 | D17: =H7 -> 15.9 | E17: =M7 -> 16.8 | F17: =R7 -> 16.4 | G17: =W7 -> 16.4 | H17: =AB7 -> 16.6 | I17: =AG7 -> 18.8 | J17: =AH7 -> 20.6 | K17: =AI7 -> 22.1 | L17: =AJ7 -> 19.0 | M17: =AK7 -> 17.6
B18: 국세 | C18: =C8 -> 26.8 | D18: =H8 -> 56.8 | E18: =M8 -> 92.9 | F18: =R8 -> 127.5 | G18: =W8 -> 177.7 | H18: =AB8 -> 217.9 | I18: =AG8 -> 285.5 | J18: =AH8 -> 344.1 | K18: =AI8 -> 395.9 | L18: =AJ8 -> 344.1 | M18: =AK8 -> 336.5
B19: 지방세 | C19: =C9 -> 6.4 | D19: =H9 -> 15.3 | E19: =M9 -> 20.6 | F19: =R9 -> 36.0 | G19: =W9 -> 49.2 | H19: =AB9 -> 71.0 | I19: =AG9 -> 102.0 | J19: =AH9 -> 112.8 | K19: =AI9 -> 118.6 | L19: =AJ9 -> 112.5 | M19: =AK9 -> 114.1

Sheet 지방재정
A3: https://www.data.go.kr/data/15038802/fileData.do?recommendDataYn=Y#
A4: https://www.lofin365.go.kr/portal/LF6100000.do?ntcaClsDvCd=FSL406&dtsSnum=655418&curPage=1
